shoestring/__init__.py
shoestring/__main__.py
shoestring/commands/__init__.py
shoestring/commands/announce_transaction.py
shoestring/commands/health.py
shoestring/commands/import_bootstrap.py
shoestring/commands/import_harvesters.py
shoestring/commands/init.py
shoestring/commands/min_cosignatures_count.py
shoestring/commands/pemtool.py
shoestring/commands/renew_certificates.py
shoestring/commands/renew_voting_keys.py
shoestring/commands/reset_data.py
shoestring/commands/setup.py
shoestring/commands/signer.py
shoestring/commands/upgrade.py
shoestring/healthagents/__init__.py
shoestring/healthagents/peer_api.py
shoestring/healthagents/peer_certificate.py
shoestring/healthagents/rest_api.py
shoestring/healthagents/rest_https_certificate.py
shoestring/healthagents/voting_keys.py
shoestring/healthagents/websockets.py
shoestring/internal/CertificateFactory.py
shoestring/internal/ConfigurationManager.py
shoestring/internal/FileDownloader.py
shoestring/internal/FileTemplater.py
shoestring/internal/HarvesterConfigurator.py
shoestring/internal/HeightGrouping.py
shoestring/internal/LinkTransactionBuilder.py
shoestring/internal/MultisigAnalyzer.py
shoestring/internal/NodeDownloader.py
shoestring/internal/NodeFeatures.py
shoestring/internal/NodeKeyUtils.py
shoestring/internal/NodewatchClient.py
shoestring/internal/OpensslExecutor.py
shoestring/internal/PackageResolver.py
shoestring/internal/PeerDownloader.py
shoestring/internal/PemUtils.py
shoestring/internal/Preparer.py
shoestring/internal/ShoestringConfiguration.py
shoestring/internal/TransactionSerializer.py
shoestring/internal/VoterConfigurator.py
shoestring/internal/__init__.py
shoestring/lang/en/LC_MESSAGES/messages.mo
shoestring/lang/en/LC_MESSAGES/messages.po
shoestring/lang/ja/LC_MESSAGES/messages.mo
shoestring/lang/ja/LC_MESSAGES/messages.po
shoestring/lang/messages.pot
shoestring/lang/po.header.txt
shoestring/startup/delayrestapi.sh
shoestring/startup/mongors.sh
shoestring/startup/startBroker.sh
symbol_shoestring-0.2.2.dist-info/METADATA
symbol_shoestring-0.2.2.dist-info/WHEEL
symbol_shoestring-0.2.2.dist-info/RECORD
