Metadata-Version: 2.1
Name: symbol-shoestring
Version: 0.2.2
Summary: Symbol Shoestring Deployment Tool
Home-page: https://github.com/symbol/product/tree/main/tools/shoestring
License: MIT
Keywords: symbol,shoestring,deployment,node
Author: Symbol Contributors
Author-email: contributors@symbol.dev
Maintainer: Symbol Contributors
Maintainer-email: contributors@symbol.dev
Requires-Python: >=3.9.2,<4.0.0
Classifier: License :: OSI Approved :: MIT License
Classifier: Programming Language :: Python :: 3
Classifier: Programming Language :: Python :: 3.10
Classifier: Programming Language :: Python :: 3.11
Classifier: Programming Language :: Python :: 3.12
Classifier: Programming Language :: Python :: 3.13
Classifier: Programming Language :: Python :: 3.9
Requires-Dist: aiohttp (>=3.12.6,<3.13.0)
Requires-Dist: jinja2 (>=3.1.2,<3.2.0)
Requires-Dist: prompt-toolkit (>=3.0.39,<3.1.0)
Requires-Dist: pyyaml (>=6.0.1,<6.1.0)
Requires-Dist: requests (>=2.32.2,<2.33.0)
Requires-Dist: symbol-lightapi (>=0.0.7,<0.1.0)
Requires-Dist: symbol-sdk-python (>=3.3.0,<3.4.0)
Requires-Dist: websockets (>=15.0,<16.0)
Requires-Dist: zenlog (>=1.1,<2.0)
Project-URL: Repository, https://github.com/symbol/product/tree/main/tools/shoestring
